{"pkgname": "arj", "pkgbase": "arj", "repo": "extra", "arch": "x86_64", "pkgver": "3.10.22", "pkgrel": "14", "epoch": 0, "pkgdesc": "Free and portable clone of the ARJ archiver", "url": "http://arj.sourceforge.net/", "filename": "arj-3.10.22-14-x86_64.pkg.tar.zst", "compressed_size": 138407, "installed_size": 319598, "build_date": "2024-09-06T19:04:05Z", "last_update": "2024-09-06T19:06:59.899Z", "flag_date": null, "maintainers": ["anthraxx"], "packager": "arojas", "groups": [], "licenses": ["GPL"], "conflicts": [], "provides": [], "replaces": [], "depends": ["glibc"], "optdepends": [], "makedepends": [], "checkdepends": []}