{"pkgname": "arrayfire", "pkgbase": "arrayfire", "repo": "extra", "arch": "x86_64", "pkgver": "3.9.0", "pkgrel": "8", "epoch": 0, "pkgdesc": "High performance software library for parallel computing with an easy-to-use API", "url": "https://arrayfire.com", "filename": "arrayfire-3.9.0-8-x86_64.pkg.tar.zst", "compressed_size": 124757963, "installed_size": 1671725087, "build_date": "2024-11-12T01:48:01Z", "last_update": "2024-11-16T05:09:27.373Z", "flag_date": null, "maintainers": ["svenstaro", "kgizdov"], "packager": "svenstaro", "groups": [], "licenses": ["BSD"], "conflicts": [], "provides": [], "replaces": [], "depends": ["cblas", "fftw", "forge", "glew", "glfw", "intel-oneapi-mkl", "intel-oneapi-tbb", "lapacke", "spdlog"], "optdepends": ["cuda: Required for using CUDA backend", "cudnn: Required for using CUDA backend", "nvidia-utils: Required for using CUDA backend", "ocl-icd: Required for OpenCL ICD Bindings", "opencl-driver: Required for using OpenCL backend"], "makedepends": ["boost", "cmake", "cuda", "cudnn", "doxygen", "git", "graphviz", "ninja", "ocl-icd", "opencl-headers", "python"], "checkdepends": []}