{"pkgname": "bftpd", "pkgbase": "bftpd", "repo": "extra", "arch": "x86_64", "pkgver": "6.1", "pkgrel": "4", "epoch": 0, "pkgdesc": "Small, easy-to-configure FTP server", "url": "http://bftpd.sourceforge.net/", "filename": "bftpd-6.1-4-x86_64.pkg.tar.zst", "compressed_size": 39067, "installed_size": 90304, "build_date": "2024-07-12T01:24:44Z", "last_update": "2024-07-12T02:07:16.101Z", "flag_date": "2024-07-22T21:10:14.263Z", "maintainers": ["anthraxx"], "packager": "blakkheim", "groups": [], "licenses": ["GPL-2.0-only"], "conflicts": [], "provides": [], "replaces": [], "depends": ["glibc", "libcrypt.so=2-64", "libxcrypt", "pam", "zlib"], "optdepends": ["logrotate: log file administration"], "makedepends": [], "checkdepends": []}