{"pkgname": "certbot-dns-hetzner", "pkgbase": "certbot-dns-hetzner", "repo": "extra", "arch": "any", "pkgver": "2.0.1", "pkgrel": "1", "epoch": 0, "pkgdesc": "Certbot plugin enabling dns-01 challenge on the Hetzner DNS API", "url": "https://github.com/ctrlaltcoop/certbot-dns-hetzner", "filename": "certbot-dns-hetzner-2.0.1-1-any.pkg.tar.zst", "compressed_size": 15426, "installed_size": 47290, "build_date": "2024-07-03T21:33:58Z", "last_update": "2024-07-03T21:56:48.486Z", "flag_date": null, "maintainers": ["hashworks"], "packager": "hashworks", "groups": [], "licenses": ["Apache-2.0"], "conflicts": [], "provides": [], "replaces": [], "depends": ["certbot", "dns-lexicon", "python-parsedatetime", "python-requests", "python-requests-mock", "python-tldextract"], "optdepends": [], "makedepends": ["python-setuptools"], "checkdepends": ["python-pytest"]}