{"pkgname": "coin", "pkgbase": "coin", "repo": "extra", "arch": "x86_64", "pkgver": "4.0.3", "pkgrel": "1", "epoch": 0, "pkgdesc": "3D graphics library compatible with Open Inventor", "url": "https://github.com/coin3d/coin", "filename": "coin-4.0.3-1-x86_64.pkg.tar.zst", "compressed_size": 5339067, "installed_size": 15137785, "build_date": "2024-09-06T15:32:06Z", "last_update": "2024-09-06T15:43:52.535Z", "flag_date": null, "maintainers": ["arodseth"], "packager": "arodseth", "groups": [], "licenses": ["BSD-3-Clause"], "conflicts": [], "provides": [], "replaces": [], "depends": ["libgl"], "optdepends": ["fontconfig: dynamic linking support", "freetype2: dynamic linking support", "openal: audio/dynamic linking support", "zlib: dynamic linking support"], "makedepends": ["boost", "cmake", "doxygen", "git", "glu", "ninja"], "checkdepends": []}