{"pkgname": "deepin-app-services", "pkgbase": "deepin-app-services", "repo": "extra", "arch": "x86_64", "pkgver": "1.0.25", "pkgrel": "1", "epoch": 0, "pkgdesc": "Service collection of DDE applications, including dconfig-center", "url": "https://github.com/linuxdeepin/dde-app-services", "filename": "deepin-app-services-1.0.25-1-x86_64.pkg.tar.zst", "compressed_size": 301967, "installed_size": 801096, "build_date": "2024-01-29T23:47:48Z", "last_update": "2024-01-29T23:51:56.950Z", "flag_date": null, "maintainers": ["felixonmars"], "packager": "felixonmars", "groups": ["deepin"], "licenses": ["GPL3"], "conflicts": [], "provides": [], "replaces": [], "depends": ["dtkcore", "dtkwidget", "qt5-base"], "optdepends": [], "makedepends": ["cmake", "doxygen", "gtest", "ninja", "qt5-tools"], "checkdepends": []}