{"pkgname": "dtk6widget", "pkgbase": "dtk6widget", "repo": "extra", "arch": "x86_64", "pkgver": "6.0.19", "pkgrel": "1", "epoch": 0, "pkgdesc": "Deepin base graphical widgets library", "url": "https://github.com/linuxdeepin/dtk6widget", "filename": "dtk6widget-6.0.19-1-x86_64.pkg.tar.zst", "compressed_size": 23467284, "installed_size": 32996957, "build_date": "2024-10-20T23:08:02Z", "last_update": "2024-10-20T23:16:45.471Z", "flag_date": null, "maintainers": ["felixonmars"], "packager": "felixonmars", "groups": [], "licenses": ["LGPL3"], "conflicts": [], "provides": [], "replaces": [], "depends": ["dtk6core", "dtk6gui", "gcc-libs", "glibc", "libx11", "libxcb", "libxext", "libxi", "qt6-base", "qt6-imageformats", "qt6-svg", "startup-notification", "xcb-util"], "optdepends": [], "makedepends": ["cmake", "doxygen", "git", "gtest", "ninja", "qt6-tools"], "checkdepends": []}