{"pkgname": "erlang-docs", "pkgbase": "erlang-docs", "repo": "extra", "arch": "any", "pkgver": "27.0", "pkgrel": "1", "epoch": 0, "pkgdesc": "HTML and PDF documentation for Erlang", "url": "http://erlang.org/doc/", "filename": "erlang-docs-27.0-1-any.pkg.tar.zst", "compressed_size": 15217262, "installed_size": 97271241, "build_date": "2024-06-14T23:57:32Z", "last_update": "2024-06-15T00:00:44.559Z", "flag_date": null, "maintainers": ["arodseth"], "packager": "arodseth", "groups": [], "licenses": ["Apache-2.0"], "conflicts": [], "provides": [], "replaces": [], "depends": [], "optdepends": [], "makedepends": [], "checkdepends": []}