{"pkgname": "esh", "pkgbase": "esh", "repo": "extra", "arch": "any", "pkgver": "0.3.2", "pkgrel": "2", "epoch": 0, "pkgdesc": "Simple templating engine based on shell", "url": "https://github.com/jirutka/esh", "filename": "esh-0.3.2-2-any.pkg.tar.zst", "compressed_size": 9485, "installed_size": 11877, "build_date": "2024-07-05T00:10:59Z", "last_update": "2024-07-05T00:14:54.295Z", "flag_date": null, "maintainers": ["alex19EP"], "packager": "Antiz", "groups": [], "licenses": ["MIT"], "conflicts": [], "provides": [], "replaces": [], "depends": ["gawk", "sed"], "optdepends": [], "makedepends": ["asciidoctor"], "checkdepends": []}