{"pkgname": "flac", "pkgbase": "flac", "repo": "extra", "arch": "x86_64", "pkgver": "1.4.3", "pkgrel": "2", "epoch": 0, "pkgdesc": "Free Lossless Audio Codec", "url": "https://xiph.org/flac/", "filename": "flac-1.4.3-2-x86_64.pkg.tar.zst", "compressed_size": 330471, "installed_size": 1185045, "build_date": "2024-07-09T20:38:58Z", "last_update": "2024-07-09T20:41:58.183Z", "flag_date": null, "maintainers": ["anthraxx", "heftig"], "packager": "blakkheim", "groups": [], "licenses": ["BSD", "GPL"], "conflicts": [], "provides": ["libFLAC++.so=10-64", "libFLAC.so=12-64"], "replaces": [], "depends": ["gcc-libs", "libogg"], "optdepends": [], "makedepends": ["cmake", "doxygen", "nasm", "ninja"], "checkdepends": []}