{"pkgname": "geary", "pkgbase": "geary", "repo": "extra", "arch": "x86_64", "pkgver": "46.0", "pkgrel": "2", "epoch": 1, "pkgdesc": "A lightweight email client for the GNOME desktop", "url": "https://wiki.gnome.org/Apps/Geary", "filename": "geary-1:46.0-2-x86_64.pkg.tar.zst", "compressed_size": 2649497, "installed_size": 12043286, "build_date": "2024-09-13T07:43:45Z", "last_update": "2024-09-13T07:53:04.388Z", "flag_date": null, "maintainers": ["alucryd"], "packager": "eworm", "groups": ["gnome-extra"], "licenses": ["CC-BY-3.0", "CC-BY-SA-3.0", "LGPL-2.1-or-later"], "conflicts": [], "provides": [], "replaces": [], "depends": ["at-spi2-core", "cairo", "dconf", "enchant", "folks", "gcr", "gdk-pixbuf2", "glib2", "glibc", "gmime3", "gnome-online-accounts", "gsound", "gspell", "gtk3", "hicolor-icon-theme", "icu", "iso-codes", "json-glib", "libgee", "libgoa", "libhandy", "libpeas", "libsecret", "libsoup3", "libstemmer", "libunwind", "libxml2", "libytnef", "org.freedesktop.secrets", "pango", "sqlite", "webkit2gtk-4.1"], "optdepends": [], "makedepends": ["appstream-glib", "cmake", "git", "gobject-introspection", "meson", "vala", "yelp-tools"], "checkdepends": []}