{"pkgname": "gitlab", "pkgbase": "gitlab", "repo": "extra", "arch": "x86_64", "pkgver": "17.5.2", "pkgrel": "1", "epoch": 0, "pkgdesc": "Project management and code hosting application", "url": "https://gitlab.com/gitlab-org/gitlab-foss", "filename": "gitlab-17.5.2-1-x86_64.pkg.tar.zst", "compressed_size": 482564937, "installed_size": 1788188619, "build_date": "2024-11-13T13:18:51Z", "last_update": "2024-11-13T14:21:10.883Z", "flag_date": null, "maintainers": ["alerque"], "packager": "alerque", "groups": [], "licenses": ["MIT"], "conflicts": ["gitlab-workhorse"], "provides": ["gitlab-workhorse"], "replaces": ["gitlab-workhorse"], "depends": ["git", "gitlab-gitaly", "gitlab-shell", "http-parser", "icu", "libicui18n.so=75-64", "libicuuc.so=75-64", "libre2.so=11-64", "libxslt", "nodejs", "openssh", "openssl", "perl-image-exiftool", "re2", "redis", "ruby", "ruby-bundler", "ruby-erb", "ruby-irb", "ruby-rdoc"], "optdepends": ["postgresql: database backend", "python-docutils: reStructuredText markup language support", "smtp-server: mail server in order to receive mail notifications"], "makedepends": ["cargo", "clang", "cmake", "go", "node-gyp", "nodejs", "postgresql", "rust", "yarn"], "checkdepends": []}