{"pkgname": "gnuchess", "pkgbase": "gnuchess", "repo": "extra", "arch": "x86_64", "pkgver": "6.2.9", "pkgrel": "3", "epoch": 0, "pkgdesc": "Play chess against the computer on a terminal and an engine for graphical chess frontends", "url": "https://www.gnu.org/software/chess/chess.html", "filename": "gnuchess-6.2.9-3-x86_64.pkg.tar.zst", "compressed_size": 232457, "installed_size": 605964, "build_date": "2022-11-14T22:56:04Z", "last_update": "2023-05-19T16:47:25.842Z", "flag_date": null, "maintainers": ["jsteel"], "packager": "kpcyrd", "groups": [], "licenses": ["GPL3"], "conflicts": [], "provides": [], "replaces": [], "depends": ["bash"], "optdepends": ["xboard: graphical frontend"], "makedepends": [], "checkdepends": []}