{"pkgname": "gradle7-src", "pkgbase": "gradle7", "repo": "extra", "arch": "any", "pkgver": "7.6.4", "pkgrel": "1", "epoch": 0, "pkgdesc": "Powerful build system for the JVM (sources)", "url": "https://gradle.org/", "filename": "gradle7-src-7.6.4-1-any.pkg.tar.zst", "compressed_size": 3629544, "installed_size": 29400906, "build_date": "2024-02-05T15:36:45Z", "last_update": "2024-02-05T16:02:19.867Z", "flag_date": null, "maintainers": [], "packager": "freswa", "groups": [], "licenses": ["Apache"], "conflicts": ["gradle-src"], "provides": ["gradle-src"], "replaces": [], "depends": ["bash", "coreutils", "findutils", "java-environment", "sed", "which"], "optdepends": [], "makedepends": ["asciidoc", "git", "groovy", "java-environment=11", "xmlto"], "checkdepends": []}