{"pkgname": "gtk-session-lock", "pkgbase": "gtk-session-lock", "repo": "extra", "arch": "x86_64", "pkgver": "0.2.0", "pkgrel": "2", "epoch": 0, "pkgdesc": "A library to create screen lockers for Wayland using the ext-session-lock protocol", "url": "https://github.com/Cu3PO42/gtk-session-lock", "filename": "gtk-session-lock-0.2.0-2-x86_64.pkg.tar.zst", "compressed_size": 14803, "installed_size": 46461, "build_date": "2024-08-17T08:23:54Z", "last_update": "2024-08-20T23:07:20.048Z", "flag_date": null, "maintainers": ["Antiz"], "packager": "Antiz", "groups": [], "licenses": ["GPL-3.0-or-later"], "conflicts": [], "provides": ["libgtk-session-lock.so=0-64"], "replaces": [], "depends": ["gtk3", "wayland"], "optdepends": [], "makedepends": ["gobject-introspection", "meson", "vala", "wayland-protocols"], "checkdepends": []}