{"pkgname": "haskell-lattices", "pkgbase": "haskell-lattices", "repo": "extra", "arch": "x86_64", "pkgver": "2.1", "pkgrel": "75", "epoch": 0, "pkgdesc": "Fine-grained library for constructing and manipulating lattices", "url": "https://github.com/phadej/lattices/", "filename": "haskell-lattices-2.1-75-x86_64.pkg.tar.zst", "compressed_size": 395150, "installed_size": 2626489, "build_date": "2024-10-23T13:02:22Z", "last_update": "2024-10-23T17:15:27.085Z", "flag_date": null, "maintainers": ["felixonmars"], "packager": "felixonmars", "groups": [], "licenses": ["BSD"], "conflicts": [], "provides": [], "replaces": [], "depends": ["ghc-libs", "haskell-base-compat", "haskell-hashable", "haskell-integer-logarithms", "haskell-quickcheck", "haskell-semigroupoids", "haskell-tagged", "haskell-universe-base", "haskell-universe-reverse-instances", "haskell-unordered-containers"], "optdepends": [], "makedepends": ["ghc", "haskell-quickcheck-instances", "haskell-tasty", "haskell-tasty-quickcheck"], "checkdepends": []}