{"pkgname": "haskell-digest", "pkgbase": "haskell-digest", "repo": "extra", "arch": "x86_64", "pkgver": "0.0.1.7", "pkgrel": "2", "epoch": 0, "pkgdesc": "Various hashes for bytestrings; CRC32 and Adler32 for now", "url": "https://github.com/TeofilC/digest", "filename": "haskell-digest-0.0.1.7-2-x86_64.pkg.tar.zst", "compressed_size": 14214, "installed_size": 43431, "build_date": "2024-02-25T21:01:45Z", "last_update": "2024-03-05T15:22:45.606Z", "flag_date": null, "maintainers": ["felixonmars"], "packager": "felixonmars", "groups": [], "licenses": ["BSD"], "conflicts": [], "provides": [], "replaces": [], "depends": ["ghc-libs", "zlib"], "optdepends": [], "makedepends": ["ghc"], "checkdepends": []}