{"pkgname": "haskell-multimap", "pkgbase": "haskell-multimap", "repo": "extra", "arch": "x86_64", "pkgver": "1.2.1", "pkgrel": "2", "epoch": 0, "pkgdesc": "A multimap", "url": "http://hub.darcs.net/scravy/multimap", "filename": "haskell-multimap-1.2.1-2-x86_64.pkg.tar.zst", "compressed_size": 39165, "installed_size": 189399, "build_date": "2024-02-25T21:03:42Z", "last_update": "2024-03-05T15:25:41.735Z", "flag_date": null, "maintainers": ["felixonmars"], "packager": "felixonmars", "groups": [], "licenses": ["MIT"], "conflicts": [], "provides": [], "replaces": [], "depends": ["ghc-libs"], "optdepends": [], "makedepends": ["ghc"], "checkdepends": []}