{"pkgname": "hyperscan", "pkgbase": "hyperscan", "repo": "extra", "arch": "x86_64", "pkgver": "5.4.2", "pkgrel": "1", "epoch": 0, "pkgdesc": "High-performance regular expression matching library", "url": "https://www.hyperscan.io", "filename": "hyperscan-5.4.2-1-x86_64.pkg.tar.zst", "compressed_size": 2356323, "installed_size": 11354605, "build_date": "2023-04-22T15:55:58Z", "last_update": "2023-05-19T16:57:55.457Z", "flag_date": null, "maintainers": ["alucryd"], "packager": "alucryd", "groups": [], "licenses": ["BSD"], "conflicts": [], "provides": [], "replaces": [], "depends": [], "optdepends": [], "makedepends": ["boost", "cmake", "git", "ninja", "python", "ragel"], "checkdepends": []}