{"pkgname": "indicator-china-weather", "pkgbase": "indicator-china-weather", "repo": "extra", "arch": "x86_64", "pkgver": "3.0.4", "pkgrel": "2", "epoch": 0, "pkgdesc": "Indicator that displays China weather information", "url": "https://github.com/UbuntuKylin/indicator-china-weather", "filename": "indicator-china-weather-3.0.4-2-x86_64.pkg.tar.zst", "compressed_size": 971104, "installed_size": 1530910, "build_date": "2024-07-12T18:32:12Z", "last_update": "2024-07-12T19:39:09.344Z", "flag_date": null, "maintainers": ["felixonmars"], "packager": "blakkheim", "groups": ["ukui"], "licenses": ["GPL"], "conflicts": [], "provides": [], "replaces": [], "depends": ["geoip", "qt5-base"], "optdepends": [], "makedepends": ["qt5-tools"], "checkdepends": []}