{"pkgname": "iptables-nft", "pkgbase": "iptables", "repo": "core", "arch": "x86_64", "pkgver": "1.8.10", "pkgrel": "2", "epoch": 1, "pkgdesc": "Linux kernel packet control tool (using nft interface)", "url": "https://www.netfilter.org/projects/iptables/index.html", "filename": "iptables-nft-1:1.8.10-2-x86_64.pkg.tar.zst", "compressed_size": 429974, "installed_size": 2451541, "build_date": "2024-07-03T16:01:49Z", "last_update": "2024-07-04T07:56:43.998Z", "flag_date": "2024-11-08T13:56:31.446Z", "maintainers": ["felixonmars"], "packager": "eworm", "groups": [], "licenses": ["GPL2"], "conflicts": ["arptables", "ebtables", "iptables"], "provides": ["arptables", "ebtables", "iptables", "libip4tc.so=2-64", "libip6tc.so=2-64", "libipq.so=0-64", "libxtables.so=12-64"], "replaces": [], "depends": ["bash", "libnetfilter_conntrack", "libnfnetlink", "libnftnl", "libpcap", "nftables"], "optdepends": [], "makedepends": ["linux-api-headers"], "checkdepends": []}