{"pkgname": "jack_capture", "pkgbase": "jack_capture", "repo": "extra", "arch": "x86_64", "pkgver": "0.9.73", "pkgrel": "8", "epoch": 0, "pkgdesc": "Simple command line tool to record JACK audio output to a file", "url": "https://github.com/kmatheussen/jack_capture", "filename": "jack_capture-0.9.73-8-x86_64.pkg.tar.zst", "compressed_size": 40694, "installed_size": 106976, "build_date": "2020-07-07T17:50:20Z", "last_update": "2023-05-19T16:58:53.116Z", "flag_date": null, "maintainers": ["dvzrv"], "packager": "felixonmars", "groups": ["pro-audio"], "licenses": ["GPL2"], "conflicts": [], "provides": [], "replaces": [], "depends": ["jack", "lame", "liblo"], "optdepends": ["zenity: gtk2 GUI"], "makedepends": [], "checkdepends": []}