{"pkgname": "jdk8-openjdk", "pkgbase": "java8-openjdk", "repo": "extra", "arch": "x86_64", "pkgver": "8.432.u05", "pkgrel": "1", "epoch": 0, "pkgdesc": "OpenJDK Java 8 development kit", "url": "https://openjdk.java.net/", "filename": "jdk8-openjdk-8.432.u05-1-x86_64.pkg.tar.zst", "compressed_size": 9032830, "installed_size": 40224062, "build_date": "2024-10-16T16:18:27Z", "last_update": "2024-10-16T16:34:39.329Z", "flag_date": null, "maintainers": ["anthraxx", "freswa", "artafinde"], "packager": "freswa", "groups": [], "licenses": ["LicenseRef-Java"], "conflicts": [], "provides": ["java-environment=8", "java-environment-openjdk=8"], "replaces": ["jdk8-openjdk-wm"], "depends": ["java-environment-common", "jre8-openjdk=8.432.u05-1"], "optdepends": ["gvfs: open links e.g. hyperlinks"], "makedepends": ["alsa-lib", "bash", "ccache", "cpio", "fontconfig", "giflib", "git", "java-environment=8", "libcups", "libxrender", "libxtst", "unzip", "zip"], "checkdepends": []}