{"pkgname": "kphotoalbum", "pkgbase": "kphotoalbum", "repo": "extra", "arch": "x86_64", "pkgver": "5.13.0", "pkgrel": "1", "epoch": 0, "pkgdesc": "KDE Photo Album, picture collection manager", "url": "https://www.kphotoalbum.org/", "filename": "kphotoalbum-5.13.0-1-x86_64.pkg.tar.zst", "compressed_size": 8200354, "installed_size": 15196422, "build_date": "2024-10-10T15:31:40Z", "last_update": "2024-10-10T15:35:17.201Z", "flag_date": null, "maintainers": ["lcarlier"], "packager": "arojas", "groups": [], "licenses": ["GPL"], "conflicts": [], "provides": [], "replaces": [], "depends": ["exiv2", "libkdcraw5", "marble-common", "perl", "purpose5"], "optdepends": [], "makedepends": ["extra-cmake-modules", "kdoctools5"], "checkdepends": []}