{"pkgname": "languagetool", "pkgbase": "languagetool", "repo": "extra", "arch": "any", "pkgver": "6.5", "pkgrel": "1", "epoch": 0, "pkgdesc": "An open source language checker", "url": "https://www.languagetool.org", "filename": "languagetool-6.5-1-any.pkg.tar.zst", "compressed_size": 229412984, "installed_size": 399377529, "build_date": "2024-09-27T16:35:04Z", "last_update": "2024-09-27T16:44:20.520Z", "flag_date": null, "maintainers": [], "packager": "arojas", "groups": [], "licenses": ["LGPL"], "conflicts": [], "provides": [], "replaces": [], "depends": ["java-runtime-headless"], "optdepends": ["gtk3: GTK style for the GUI", "java-runtime: needed for the GUI version", "libxtst: needed for the GUI version"], "makedepends": ["unzip"], "checkdepends": []}