{"pkgname": "libchewing", "pkgbase": "libchewing", "repo": "extra", "arch": "x86_64", "pkgver": "0.9.1", "pkgrel": "1", "epoch": 0, "pkgdesc": "Intelligent Chinese phonetic input method", "url": "https://chewing.im/", "filename": "libchewing-0.9.1-1-x86_64.pkg.tar.zst", "compressed_size": 2436429, "installed_size": 7037731, "build_date": "2024-10-26T11:28:46Z", "last_update": "2024-10-29T13:51:59.470Z", "flag_date": null, "maintainers": ["yan12125"], "packager": "yan12125", "groups": [], "licenses": ["LGPL-2.1-or-later"], "conflicts": [], "provides": [], "replaces": [], "depends": ["sqlite"], "optdepends": ["chewing-editor: view and modify libchewing user phrases database"], "makedepends": ["cmake", "corrosion", "minisign", "rust"], "checkdepends": []}