{"pkgname": "libportal", "pkgbase": "libportal", "repo": "extra", "arch": "x86_64", "pkgver": "0.8.1", "pkgrel": "1", "epoch": 0, "pkgdesc": "GIO-style async APIs for most Flatpak portals", "url": "https://github.com/flatpak/libportal", "filename": "libportal-0.8.1-1-x86_64.pkg.tar.zst", "compressed_size": 96664, "installed_size": 584455, "build_date": "2024-09-05T12:03:47Z", "last_update": "2024-09-05T12:07:39.109Z", "flag_date": null, "maintainers": ["heftig"], "packager": "heftig", "groups": [], "licenses": ["LGPL-3.0-only"], "conflicts": [], "provides": ["libportal.so=1-64"], "replaces": [], "depends": ["gcc-libs", "glib2", "glibc", "libgio-2.0.so=0-64", "libglib-2.0.so=0-64", "libgobject-2.0.so=0-64"], "optdepends": ["libportal-docs: API documentation", "libportal-gtk3: GTK 3 backend", "libportal-gtk4: GTK 4 backend", "libportal-qt5: Qt 5 backend", "libportal-qt6: Qt 6 backend", "xdg-desktop-portal: Portal service"], "makedepends": ["gcc-libs", "gi-docgen", "git", "gjs", "glib2", "glib2-devel", "glibc", "gobject-introspection", "gtk3", "gtk4", "meson", "qt5-base", "qt5-tools", "qt5-x11extras", "qt6-base", "qt6-tools", "vala"], "checkdepends": ["python-dbusmock", "python-pytest", "xorg-server-xvfb"]}