{"pkgname": "libsass", "pkgbase": "libsass", "repo": "extra", "arch": "x86_64", "pkgver": "3.6.6", "pkgrel": "1", "epoch": 0, "pkgdesc": "C implementation of Sass CSS preprocessor (library)", "url": "https://sass-lang.com/libsass/", "filename": "libsass-3.6.6-1-x86_64.pkg.tar.zst", "compressed_size": 675968, "installed_size": 2288656, "build_date": "2023-12-22T20:53:54Z", "last_update": "2023-12-22T20:56:55.284Z", "flag_date": null, "maintainers": ["alerque"], "packager": "alerque", "groups": [], "licenses": ["MIT"], "conflicts": [], "provides": [], "replaces": [], "depends": [], "optdepends": [], "makedepends": [], "checkdepends": []}