{"pkgname": "libxcrypt-compat", "pkgbase": "libxcrypt", "repo": "core", "arch": "x86_64", "pkgver": "4.4.36", "pkgrel": "2", "epoch": 0, "pkgdesc": "Modern library for one-way hashing of passwords - legacy API functions", "url": "https://github.com/besser82/libxcrypt/", "filename": "libxcrypt-compat-4.4.36-2-x86_64.pkg.tar.zst", "compressed_size": 69729, "installed_size": 178200, "build_date": "2024-07-23T18:28:32Z", "last_update": "2024-07-24T10:11:45.360Z", "flag_date": null, "maintainers": ["eworm"], "packager": "eworm", "groups": [], "licenses": ["LGPL"], "conflicts": [], "provides": ["libcrypt.so=1-64"], "replaces": [], "depends": ["libxcrypt"], "optdepends": [], "makedepends": [], "checkdepends": []}