{"pkgname": "materialx", "pkgbase": "materialx", "repo": "extra", "arch": "x86_64", "pkgver": "1.38.10", "pkgrel": "5", "epoch": 0, "pkgdesc": "Open standard for representing rich material and look-development content in computer graphics", "url": "https://materialx.org/", "filename": "materialx-1.38.10-5-x86_64.pkg.tar.zst", "compressed_size": 81856979, "installed_size": 154770743, "build_date": "2024-10-10T14:48:14Z", "last_update": "2024-10-10T15:28:25.795Z", "flag_date": null, "maintainers": ["svenstaro"], "packager": "svenstaro", "groups": [], "licenses": ["Apache"], "conflicts": [], "provides": [], "replaces": [], "depends": ["dos2unix", "gcc-libs", "glfw", "glibc", "libglvnd", "libx11", "libxt", "opencolorio", "python", "python-setuptools", "zenity"], "optdepends": [], "makedepends": ["chrpath", "cmake", "libxcursor", "libxinerama", "ninja", "pybind11"], "checkdepends": []}