{"pkgname": "nautilus-share", "pkgbase": "nautilus-share", "repo": "extra", "arch": "x86_64", "pkgver": "0.7.5", "pkgrel": "5", "epoch": 0, "pkgdesc": "Nautilus extension to share folder using Samba", "url": "https://gitlab.gnome.org/coreyberla/nautilus-share", "filename": "nautilus-share-0.7.5-5-x86_64.pkg.tar.zst", "compressed_size": 67142, "installed_size": 314068, "build_date": "2024-07-24T05:38:35Z", "last_update": "2024-07-24T05:41:16.463Z", "flag_date": null, "maintainers": ["bgyorgy"], "packager": "bgyorgy", "groups": [], "licenses": ["GPL-2.0-or-later"], "conflicts": [], "provides": [], "replaces": [], "depends": ["glib2", "glibc", "gtk4", "libnautilus-extension", "nautilus", "samba"], "optdepends": [], "makedepends": ["git", "meson"], "checkdepends": []}