{"pkgname": "nauty", "pkgbase": "nauty", "repo": "extra", "arch": "x86_64", "pkgver": "2.8.9", "pkgrel": "2", "epoch": 1, "pkgdesc": "A program for computing automorphism groups of graphs and digraphs", "url": "http://pallini.di.uniroma1.it/", "filename": "nauty-1:2.8.9-2-x86_64.pkg.tar.zst", "compressed_size": 1975665, "installed_size": 10709812, "build_date": "2024-08-25T14:26:39Z", "last_update": "2024-08-25T14:29:23.960Z", "flag_date": null, "maintainers": ["arojas"], "packager": "arojas", "groups": [], "licenses": ["Apache-2.0"], "conflicts": [], "provides": [], "replaces": [], "depends": ["glibc"], "optdepends": [], "makedepends": [], "checkdepends": []}