{"pkgname": "openmw", "pkgbase": "openmw", "repo": "extra", "arch": "x86_64", "pkgver": "0.48.0", "pkgrel": "9", "epoch": 0, "pkgdesc": "Open-source engine reimplementation for the role-playing game Morrowind", "url": "http://www.openmw.org", "filename": "openmw-0.48.0-9-x86_64.pkg.tar.zst", "compressed_size": 10951913, "installed_size": 41595815, "build_date": "2024-08-30T20:13:12Z", "last_update": "2024-09-02T16:01:46.222Z", "flag_date": null, "maintainers": ["svenstaro"], "packager": "arojas", "groups": [], "licenses": ["GPL3", "MIT", "custom"], "conflicts": [], "provides": [], "replaces": [], "depends": ["boost-libs", "bullet-dp", "ffmpeg4.4", "libxt", "luajit", "mygui", "openal", "openscenegraph", "qt5-base", "sdl2", "unshield", "yaml-cpp"], "optdepends": [], "makedepends": ["boost", "cmake", "doxygen", "ninja"], "checkdepends": []}