{"pkgname": "opentoonz", "pkgbase": "opentoonz", "repo": "extra", "arch": "x86_64", "pkgver": "1.7.1", "pkgrel": "4", "epoch": 0, "pkgdesc": "Software for producing a 2D animation", "url": "https://opentoonz.github.io/e/", "filename": "opentoonz-1.7.1-4-x86_64.pkg.tar.zst", "compressed_size": 28238548, "installed_size": 64286536, "build_date": "2024-06-21T22:50:56Z", "last_update": "2024-06-22T12:03:15.208Z", "flag_date": null, "maintainers": ["bgyorgy"], "packager": "arojas", "groups": [], "licenses": ["BSD"], "conflicts": [], "provides": [], "replaces": [], "depends": ["cblas", "ffmpeg", "freeglut", "glew", "libmypaint", "opencv", "qt5-multimedia", "qt5-script", "qt5-serialport", "qt5-svg", "superlu"], "optdepends": [], "makedepends": ["boost", "cmake", "ninja", "qt5-tools"], "checkdepends": []}