{"pkgname": "perl-config-autoconf", "pkgbase": "perl-config-autoconf", "repo": "extra", "arch": "any", "pkgver": "0.320", "pkgrel": "5", "epoch": 0, "pkgdesc": "A module to implement some of AutoConf macros in pure perl.", "url": "https://metacpan.org/release/Config-AutoConf", "filename": "perl-config-autoconf-0.320-5-any.pkg.tar.zst", "compressed_size": 37433, "installed_size": 137084, "build_date": "2024-09-01T15:29:15Z", "last_update": "2024-09-04T19:34:37.621Z", "flag_date": null, "maintainers": [], "packager": "arojas", "groups": [], "licenses": ["GPL", "PerlArtistic"], "conflicts": [], "provides": [], "replaces": [], "depends": ["perl-capture-tiny", "perl-file-slurper"], "optdepends": [], "makedepends": ["bison", "flex", "gawk", "grep", "pkg-config", "sed"], "checkdepends": []}