{"pkgname": "perl-devel-checkbin", "pkgbase": "perl-devel-checkbin", "repo": "extra", "arch": "any", "pkgver": "0.04", "pkgrel": "11", "epoch": 0, "pkgdesc": "check that a command is available", "url": "https://metacpan.org/release/Devel-CheckBin", "filename": "perl-devel-checkbin-0.04-11-any.pkg.tar.zst", "compressed_size": 4855, "installed_size": 3123, "build_date": "2024-09-01T15:54:56Z", "last_update": "2024-09-04T19:34:53.350Z", "flag_date": null, "maintainers": [], "packager": "arojas", "groups": [], "licenses": ["GPL", "PerlArtistic"], "conflicts": [], "provides": [], "replaces": [], "depends": ["perl>=5.8.1"], "optdepends": [], "makedepends": ["perl-extutils-makemaker>=6.64"], "checkdepends": []}