{"pkgname": "perl-string-crc32", "pkgbase": "perl-string-crc32", "repo": "extra", "arch": "x86_64", "pkgver": "2.100", "pkgrel": "4", "epoch": 0, "pkgdesc": "Perl/CPAN Module String::CRC32 : ZMODEMlike CRC32 generation", "url": "https://search.cpan.org/dist/String-CRC32", "filename": "perl-string-crc32-2.100-4-x86_64.pkg.tar.zst", "compressed_size": 30786, "installed_size": 62899, "build_date": "2024-09-01T18:00:02Z", "last_update": "2024-09-04T19:38:06.480Z", "flag_date": null, "maintainers": ["spupykin"], "packager": "arojas", "groups": [], "licenses": ["GPL", "PerlArtistic"], "conflicts": [], "provides": [], "replaces": [], "depends": [], "optdepends": [], "makedepends": [], "checkdepends": []}