{"pkgname": "phpmyadmin", "pkgbase": "phpmyadmin", "repo": "extra", "arch": "any", "pkgver": "5.2.1", "pkgrel": "2", "epoch": 0, "pkgdesc": "PHP and hence web-based tool to administrate MySQL over the WWW", "url": "https://www.phpmyadmin.net", "filename": "phpmyadmin-5.2.1-2-any.pkg.tar.zst", "compressed_size": 7927770, "installed_size": 50053441, "build_date": "2024-08-04T20:11:33Z", "last_update": "2024-08-04T20:15:42.704Z", "flag_date": null, "maintainers": ["spupykin"], "packager": "spupykin", "groups": [], "licenses": ["GPL"], "conflicts": [], "provides": [], "replaces": [], "depends": ["mysql-clients", "php"], "optdepends": [], "makedepends": [], "checkdepends": []}