{"pkgname": "pixi", "pkgbase": "pixi", "repo": "extra", "arch": "x86_64", "pkgver": "0.37.0", "pkgrel": "1", "epoch": 0, "pkgdesc": "A package management and workflow tool", "url": "https://github.com/prefix-dev/pixi", "filename": "pixi-0.37.0-1-x86_64.pkg.tar.zst", "compressed_size": 12975934, "installed_size": 49638664, "build_date": "2024-11-18T15:26:13Z", "last_update": "2024-11-18T15:50:48.577Z", "flag_date": null, "maintainers": ["orhun", "alerque"], "packager": "orhun", "groups": [], "licenses": ["BSD-3-Clause"], "conflicts": [], "provides": [], "replaces": [], "depends": ["bzip2", "gcc-libs", "openssl"], "optdepends": [], "makedepends": ["cargo"], "checkdepends": []}