{"pkgname": "powerdns", "pkgbase": "powerdns", "repo": "extra", "arch": "x86_64", "pkgver": "4.9.2", "pkgrel": "1", "epoch": 0, "pkgdesc": "Authoritative DNS server", "url": "https://www.powerdns.com/", "filename": "powerdns-4.9.2-1-x86_64.pkg.tar.zst", "compressed_size": 4782432, "installed_size": 20953907, "build_date": "2024-10-01T08:35:54Z", "last_update": "2024-10-01T10:45:43.029Z", "flag_date": null, "maintainers": ["anthraxx", "rgacogne", "foxxx0"], "packager": "rgacogne", "groups": [], "licenses": ["GPL-2.0-only"], "conflicts": ["pdns"], "provides": ["pdns"], "replaces": [], "depends": ["boost-libs", "gnutls", "libcurl.so=4-64", "libsodium", "lmdb", "luajit", "openssl", "sqlite", "systemd-libs"], "optdepends": ["geoip: GeoIP backend", "libldap: LDAP backend", "libmaxminddb: MaxMindDB GeoIP2 database for the GeoIP backend", "mariadb-libs: MariaDB/MySQL and MyDNS backend", "postgresql-libs: PostgreSQL backend", "tinycdb: TinyDNS backend", "unixodbc: ODBC backend", "yaml-cpp: GeoIP backend"], "makedepends": ["boost", "curl", "geoip", "libldap", "libmaxminddb", "mariadb-libs", "postgresql-libs", "systemd", "tinycdb", "unixodbc", "yaml-cpp"], "checkdepends": []}