{"pkgname": "python-clarabel", "pkgbase": "python-clarabel", "repo": "extra", "arch": "x86_64", "pkgver": "0.9.0", "pkgrel": "1", "epoch": 0, "pkgdesc": "Interior-point solver for convex conic optimisation problems", "url": "https://github.com/oxfordcontrol/Clarabel.rs", "filename": "python-clarabel-0.9.0-1-x86_64.pkg.tar.zst", "compressed_size": 750066, "installed_size": 2136881, "build_date": "2024-06-01T22:00:34Z", "last_update": "2024-06-01T22:03:29.970Z", "flag_date": null, "maintainers": ["arojas"], "packager": "arojas", "groups": [], "licenses": ["Apache-2.0"], "conflicts": [], "provides": [], "replaces": [], "depends": ["gcc-libs", "glibc"], "optdepends": [], "makedepends": ["git", "python-build", "python-installer", "python-maturin", "rust"], "checkdepends": []}