{"pkgname": "python-flask-marshmallow", "pkgbase": "python-flask-marshmallow", "repo": "extra", "arch": "any", "pkgver": "1.2.1", "pkgrel": "2", "epoch": 0, "pkgdesc": "Flask + marshmallow for beautiful APIs", "url": "https://flask-marshmallow.readthedocs.io/", "filename": "python-flask-marshmallow-1.2.1-2-any.pkg.tar.zst", "compressed_size": 23515, "installed_size": 99525, "build_date": "2024-04-06T16:29:00Z", "last_update": "2024-04-27T10:08:01.574Z", "flag_date": null, "maintainers": ["alucryd"], "packager": "jelle", "groups": [], "licenses": ["MIT"], "conflicts": [], "provides": [], "replaces": [], "depends": ["python-flask", "python-marshmallow"], "optdepends": [], "makedepends": ["git", "python-build", "python-flit-core", "python-installer"], "checkdepends": []}