{"pkgname": "qca-qt5", "pkgbase": "qca", "repo": "extra", "arch": "x86_64", "pkgver": "2.3.9", "pkgrel": "3", "epoch": 0, "pkgdesc": "Qt Cryptographic Architecture", "url": "https://userbase.kde.org/QCA", "filename": "qca-qt5-2.3.9-3-x86_64.pkg.tar.zst", "compressed_size": 789490, "installed_size": 3094307, "build_date": "2024-10-22T06:21:59Z", "last_update": "2024-10-22T06:25:49.159Z", "flag_date": null, "maintainers": ["arojas"], "packager": "arojas", "groups": [], "licenses": ["LGPL-2.1-or-later"], "conflicts": ["qca"], "provides": ["qca"], "replaces": ["qca"], "depends": ["ca-certificates", "gcc-libs", "glibc", "nss", "qt5-base"], "optdepends": ["botan: botan plugin", "libgcrypt: gcrypt plugin", "libsasl: SASL plugin", "openssl: SSL plugin", "pkcs11-helper: PKCS-11 plugin"], "makedepends": ["botan", "cmake", "doxygen", "libgcrypt", "libsasl", "openssl", "pkcs11-helper", "qt5-base", "qt6-5compat", "qt6-base"], "checkdepends": []}