{"pkgname": "qt5-multimedia", "pkgbase": "qt5-multimedia", "repo": "extra", "arch": "x86_64", "pkgver": "5.15.15+kde+r2", "pkgrel": "1", "epoch": 0, "pkgdesc": "Classes for audio, video, radio and camera functionality", "url": "https://www.qt.io", "filename": "qt5-multimedia-5.15.15+kde+r2-1-x86_64.pkg.tar.zst", "compressed_size": 758014, "installed_size": 3545839, "build_date": "2024-09-03T20:16:03Z", "last_update": "2024-09-04T14:37:46.148Z", "flag_date": null, "maintainers": ["arojas", "felixonmars"], "packager": "arojas", "groups": ["qt5"], "licenses": ["FDL", "GPL3", "LGPL3", "custom"], "conflicts": [], "provides": [], "replaces": [], "depends": ["gst-plugins-base", "libpulse", "openal", "qt5-base"], "optdepends": ["gst-libav: ffmpeg plugin", "gst-plugins-bad: camera support, additional plugins", "gst-plugins-good: camera support, additional plugins", "gst-plugins-ugly: additional plugins", "qt5-declarative: QML bindings"], "makedepends": ["git", "gst-plugins-bad", "qt5-declarative"], "checkdepends": []}