{"pkgname": "reprotest", "pkgbase": "reprotest", "repo": "extra", "arch": "any", "pkgver": "0.7.28", "pkgrel": "1", "epoch": 0, "pkgdesc": "Run a process twice and check the output for reproducibility", "url": "https://salsa.debian.org/reproducible-builds/reprotest", "filename": "reprotest-0.7.28-1-any.pkg.tar.zst", "compressed_size": 162617, "installed_size": 764247, "build_date": "2024-09-08T14:31:35Z", "last_update": "2024-09-08T14:36:40.746Z", "flag_date": null, "maintainers": ["jelle", "sangy", "anthraxx"], "packager": "jelle", "groups": [], "licenses": ["GPL3"], "conflicts": [], "provides": [], "replaces": [], "depends": ["diffoscope", "fakeroot", "libfaketime", "python", "python-distro", "python-rstr", "python-setuptools", "python-wheel"], "optdepends": ["disorderfs: to enable the shuffle-dirents option", "python-progressbar: to show a progress bar during diffoscope"], "makedepends": ["git", "help2man", "python-docutils"], "checkdepends": ["disorderfs", "python-pytest"]}