{"pkgname": "rime-cangjie", "pkgbase": "rime-cangjie", "repo": "extra", "arch": "x86_64", "pkgver": "0.0.0.20240325", "pkgrel": "1", "epoch": 0, "pkgdesc": "Cangjie input for rime", "url": "https://github.com/rime/rime-cangjie", "filename": "rime-cangjie-0.0.0.20240325-1-x86_64.pkg.tar.zst", "compressed_size": 5647219, "installed_size": 15316073, "build_date": "2024-07-22T20:01:28Z", "last_update": "2024-07-22T20:03:39.144Z", "flag_date": null, "maintainers": ["felixonmars"], "packager": "felixonmars", "groups": [], "licenses": ["LGPL"], "conflicts": [], "provides": [], "replaces": [], "depends": ["rime-luna-pinyin"], "optdepends": [], "makedepends": ["git", "librime", "rime-essay", "rime-prelude"], "checkdepends": []}