{"pkgname": "ropper", "pkgbase": "ropper", "repo": "extra", "arch": "any", "pkgver": "1.13.10", "pkgrel": "1", "epoch": 0, "pkgdesc": "Show information about binary files and find gadgets to build rop chains for different architectures", "url": "https://github.com/sashs/Ropper", "filename": "ropper-1.13.10-1-any.pkg.tar.zst", "compressed_size": 197517, "installed_size": 1347247, "build_date": "2024-05-11T22:06:21Z", "last_update": "2024-05-11T22:08:29.577Z", "flag_date": null, "maintainers": ["anthraxx"], "packager": "anthraxx", "groups": [], "licenses": ["BSD-3-Clause"], "conflicts": ["python-ropper"], "provides": ["python-ropper"], "replaces": ["python-ropper"], "depends": ["python", "python-archinfo", "python-capstone", "python-filebytes", "python-pyvex", "python-z3-solver"], "optdepends": ["python-keystone: assemble command support"], "makedepends": ["python-build", "python-installer", "python-setuptools", "python-wheel"], "checkdepends": ["python-pytest"]}