{"pkgname": "rst2pdf", "pkgbase": "rst2pdf", "repo": "extra", "arch": "any", "pkgver": "0.102", "pkgrel": "1", "epoch": 0, "pkgdesc": "Use a text editor. Make a PDF", "url": "https://github.com/rst2pdf/rst2pdf", "filename": "rst2pdf-0.102-1-any.pkg.tar.zst", "compressed_size": 308870, "installed_size": 1642329, "build_date": "2024-06-06T17:02:27Z", "last_update": "2024-06-06T17:13:07.139Z", "flag_date": null, "maintainers": ["dvzrv"], "packager": "dvzrv", "groups": [], "licenses": ["MIT"], "conflicts": [], "provides": [], "replaces": [], "depends": ["python", "python-docutils", "python-importlib-metadata", "python-jinja", "python-packaging", "python-pillow", "python-pygments", "python-reportlab", "python-smartypants", "python-yaml"], "optdepends": ["plantuml: for UML diagram support", "python-aafigure: for ASCII image support", "python-matplotlib: for math support", "python-pyphen: for hyphenation support", "python-sphinx: for sphinx support", "python-svglib: for SVG support"], "makedepends": ["python-build", "python-installer", "python-setuptools-scm", "python-wheel"], "checkdepends": ["graphviz", "plantuml", "python-aafigure", "python-matplotlib", "python-pymupdf", "python-pytest", "python-sphinx", "python-svglib"]}