{"pkgname": "ruby-sass-embedded", "pkgbase": "ruby-sass-embedded", "repo": "extra", "arch": "any", "pkgver": "1.79.4", "pkgrel": "1", "epoch": 0, "pkgdesc": "Embedded Sass Host for Ruby", "url": "https://github.com/sass-contrib/sass-embedded-host-ruby", "filename": "ruby-sass-embedded-1.79.4-1-any.pkg.tar.zst", "compressed_size": 112347, "installed_size": 518091, "build_date": "2024-10-03T15:07:13Z", "last_update": "2024-10-14T14:24:23.948Z", "flag_date": null, "maintainers": ["bertptrs"], "packager": "Segaja", "groups": [], "licenses": ["MIT"], "conflicts": [], "provides": [], "replaces": [], "depends": ["dart-sass", "ruby", "ruby-google-protobuf"], "optdepends": [], "makedepends": ["protobuf", "ruby-rake", "ruby-rdoc"], "checkdepends": ["ruby-bundler", "ruby-rspec"]}