{"pkgname": "ruby-chef-utils", "pkgbase": "ruby-chef-utils", "repo": "extra", "arch": "any", "pkgver": "19.0.44", "pkgrel": "1", "epoch": 0, "pkgdesc": "Basic utility functions for Core Chef Infra development", "url": "https://github.com/chef/chef", "filename": "ruby-chef-utils-19.0.44-1-any.pkg.tar.zst", "compressed_size": 64463, "installed_size": 324663, "build_date": "2024-10-28T22:37:10Z", "last_update": "2024-10-28T22:47:34.873Z", "flag_date": null, "maintainers": ["grawlinson"], "packager": "grawlinson", "groups": [], "licenses": ["Apache-2.0"], "conflicts": [], "provides": [], "replaces": [], "depends": ["ruby", "ruby-concurrent"], "optdepends": [], "makedepends": ["git", "ruby-bundler", "ruby-rake", "ruby-rdoc"], "checkdepends": []}