{"pkgname": "ruby-memoist", "pkgbase": "ruby-memoist", "repo": "extra", "arch": "any", "pkgver": "0.16.2", "pkgrel": "2", "epoch": 0, "pkgdesc": "ActiveSupport::Memoizable with a few enhancements", "url": "https://github.com/matthewrudy/memoist", "filename": "ruby-memoist-0.16.2-2-any.pkg.tar.zst", "compressed_size": 15550, "installed_size": 48654, "build_date": "2024-10-03T10:59:57Z", "last_update": "2024-10-14T14:23:18.819Z", "flag_date": null, "maintainers": ["bastelfreak"], "packager": "Segaja", "groups": [], "licenses": ["MIT"], "conflicts": [], "provides": [], "replaces": [], "depends": ["ruby"], "optdepends": [], "makedepends": ["ruby-rdoc"], "checkdepends": ["ruby-bundler", "ruby-minitest", "ruby-rake"]}