{"pkgname": "talkfilters", "pkgbase": "talkfilters", "repo": "extra", "arch": "x86_64", "pkgver": "2.3.8", "pkgrel": "7", "epoch": 0, "pkgdesc": "Filters to translate text into dialects that GNU finds funny", "url": "http://www.hyperrealm.com/main.php?s=talkfilters", "filename": "talkfilters-2.3.8-7-x86_64.pkg.tar.zst", "compressed_size": 298700, "installed_size": 1566316, "build_date": "2022-03-02T17:50:03Z", "last_update": "2023-05-19T17:21:12.424Z", "flag_date": null, "maintainers": ["cbehan"], "packager": "cbehan", "groups": [], "licenses": ["GPL2"], "conflicts": [], "provides": [], "replaces": [], "depends": ["glibc"], "optdepends": [], "makedepends": [], "checkdepends": []}