{"pkgname": "tang", "pkgbase": "tang", "repo": "extra", "arch": "x86_64", "pkgver": "14", "pkgrel": "1", "epoch": 0, "pkgdesc": "Server for binding data to network presence", "url": "https://github.com/latchset/tang", "filename": "tang-14-1-x86_64.pkg.tar.zst", "compressed_size": 35330, "installed_size": 85846, "build_date": "2023-12-26T09:23:37Z", "last_update": "2023-12-26T09:26:48.046Z", "flag_date": null, "maintainers": [], "packager": "arojas", "groups": [], "licenses": ["GPL3"], "conflicts": [], "provides": [], "replaces": [], "depends": ["http-parser", "jose"], "optdepends": [], "makedepends": ["asciidoc", "git", "meson"], "checkdepends": ["systemd"]}