{"pkgname": "texlive-fontutils", "pkgbase": "texlive-texmf", "repo": "extra", "arch": "any", "pkgver": "2024.2", "pkgrel": "3", "epoch": 0, "pkgdesc": "TeX Live - Graphics and font utilities", "url": "https://tug.org/texlive/", "filename": "texlive-fontutils-2024.2-3-any.pkg.tar.zst", "compressed_size": 5365048, "installed_size": 7885614, "build_date": "2024-09-26T11:25:26Z", "last_update": "2024-09-26T13:00:03.961Z", "flag_date": null, "maintainers": ["arojas", "alerque"], "packager": "arojas", "groups": ["texlive"], "licenses": ["GPL"], "conflicts": [], "provides": ["texlive-accfonts", "texlive-afm2pl", "texlive-albatross", "texlive-dosepsbin", "texlive-dvipsconfig", "texlive-epstopdf", "texlive-fontinst", "texlive-fontools", "texlive-fontware", "texlive-lcdftypetools", "texlive-luafindfont", "texlive-metatype1", "texlive-mf2pt1", "texlive-ps2eps", "texlive-ps2pk", "texlive-psutils", "texlive-t1utils", "texlive-ttfutils"], "replaces": [], "depends": ["texlive-basic", "texlive-bin"], "optdepends": ["ghostscript: for epstopdf"], "makedepends": ["subversion"], "checkdepends": []}