{"pkgname": "topcom", "pkgbase": "topcom", "repo": "extra", "arch": "x86_64", "pkgver": "1.1.2", "pkgrel": "2", "epoch": 0, "pkgdesc": "A package for computing Triangulations Of Point Configurations and Oriented Matroids", "url": "https://www.wm.uni-bayreuth.de/de/team/rambau_joerg/TOPCOM/index.html", "filename": "topcom-1.1.2-2-x86_64.pkg.tar.zst", "compressed_size": 2516893, "installed_size": 23250923, "build_date": "2024-03-11T21:04:42Z", "last_update": "2024-03-11T21:09:14.918Z", "flag_date": null, "maintainers": ["arojas"], "packager": "arojas", "groups": [], "licenses": ["GPL-2.0-or-later"], "conflicts": [], "provides": [], "replaces": [], "depends": ["gcc-libs", "glibc", "gmp"], "optdepends": [], "makedepends": [], "checkdepends": []}