{"pkgname": "transmission-cli", "pkgbase": "transmission", "repo": "extra", "arch": "x86_64", "pkgver": "4.0.6", "pkgrel": "2", "epoch": 0, "pkgdesc": "Fast, easy, and free BitTorrent client (CLI tools, daemon and web client)", "url": "http://www.transmissionbt.com/", "filename": "transmission-cli-4.0.6-2-x86_64.pkg.tar.zst", "compressed_size": 1277356, "installed_size": 5454451, "build_date": "2024-06-29T21:54:05Z", "last_update": "2024-06-29T21:59:27.548Z", "flag_date": null, "maintainers": ["alerque"], "packager": "arojas", "groups": [], "licenses": ["GPL"], "conflicts": [], "provides": [], "replaces": [], "depends": ["curl", "libb64", "libdeflate", "libevent", "libnatpmp", "miniupnpc", "systemd"], "optdepends": [], "makedepends": ["cmake", "curl", "dht", "glibmm-2.68", "gtk4", "gtkmm-4.0", "intltool", "libb64", "libdeflate", "libevent", "libnatpmp", "miniupnpc", "ninja", "npm", "qt6-base", "qt6-svg", "qt6-tools", "systemd"], "checkdepends": []}