{"pkgname": "ttf-inconsolata-nerd", "pkgbase": "nerd-fonts", "repo": "extra", "arch": "any", "pkgver": "3.3.0", "pkgrel": "1", "epoch": 0, "pkgdesc": "Patched font Inconsolata from nerd fonts library", "url": "https://github.com/ryanoasis/nerd-fonts", "filename": "ttf-inconsolata-nerd-3.3.0-1-any.pkg.tar.zst", "compressed_size": 2106825, "installed_size": 13621710, "build_date": "2024-11-18T15:53:20Z", "last_update": "2024-11-18T16:14:55.337Z", "flag_date": null, "maintainers": ["blakkheim"], "packager": "blakkheim", "groups": ["nerd-fonts"], "licenses": ["OFL-1.1-no-RFN"], "conflicts": ["nerd-fonts-inconsolata"], "provides": ["ttf-font-nerd"], "replaces": ["nerd-fonts-inconsolata"], "depends": [], "optdepends": [], "makedepends": [], "checkdepends": []}