{"pkgname": "whipper", "pkgbase": "whipper", "repo": "extra", "arch": "x86_64", "pkgver": "0.10.0", "pkgrel": "6", "epoch": 0, "pkgdesc": "Python CD-DA ripper preferring accuracy over speed", "url": "https://github.com/whipper-team/whipper", "filename": "whipper-0.10.0-6-x86_64.pkg.tar.zst", "compressed_size": 236943, "installed_size": 1358882, "build_date": "2024-04-12T21:16:13Z", "last_update": "2024-04-27T10:41:46.683Z", "flag_date": null, "maintainers": ["shibumi", "Archange"], "packager": "arojas", "groups": [], "licenses": ["GPL3"], "conflicts": ["accuraterip-checksum"], "provides": ["accuraterip-checksum"], "replaces": [], "depends": ["cdrdao", "flac", "libcdio-paranoia", "libsndfile", "python-discid", "python-gobject", "python-musicbrainzngs", "python-mutagen", "python-pycdio", "python-ruamel-yaml", "python-setuptools", "sox"], "optdepends": ["python-pillow: cover art support"], "makedepends": ["python-docutils", "python-setuptools-scm"], "checkdepends": ["python-twisted"]}