{"pkgname": "whowatch", "pkgbase": "whowatch", "repo": "extra", "arch": "x86_64", "pkgver": "1.8.6", "pkgrel": "3", "epoch": 0, "pkgdesc": "Displays information about the users currently logged on to the machine in real time", "url": "https://wizard.uek.krakow.pl/~mike/#whowatch", "filename": "whowatch-1.8.6-3-x86_64.pkg.tar.zst", "compressed_size": 27665, "installed_size": 61879, "build_date": "2024-07-14T02:03:40Z", "last_update": "2024-07-14T02:20:36.524Z", "flag_date": null, "maintainers": ["anthraxx"], "packager": "blakkheim", "groups": [], "licenses": ["GPL2"], "conflicts": [], "provides": [], "replaces": [], "depends": ["glibc", "ncurses"], "optdepends": [], "makedepends": [], "checkdepends": []}